casrel_datautils/Base_Conf.py
casrel_datautils/__init__.py
casrel_datautils/data_loader.py
casrel_datautils/process.py
tests/__init__.py
tests/tools_demo_已测.py
casrel_datautils-1.1.5.dist-info/License
casrel_datautils-1.1.5.dist-info/METADATA
casrel_datautils-1.1.5.dist-info/WHEEL
casrel_datautils-1.1.5.dist-info/top_level.txt
casrel_datautils-1.1.5.dist-info/RECORD
